<annotation>
	<folder>mung_bean_sprouts</folder>
	<filename>mung_bean_sprouts_23.jpg</filename>
	<path>/Users/AndyWu/Documents/Docker/TensorFlow/chinese-cafeteria-food-recognition/10_22_19_food/mung_bean_sprouts/mung_bean_sprouts_23.jpg</path>
	<source>
		<database>Unknown</database>
	</source>
	<size>
		<width>1108</width>
		<height>1478</height>
		<depth>3</depth>
	</size>
	<segmented>0</segmented>
	<object>
		<name>mung_bean_sprouts</name>
		<pose>Unspecified</pose>
		<truncated>0</truncated>
		<difficult>0</difficult>
		<bndbox>
			<xmin>490</xmin>
			<ymin>712</ymin>
			<xmax>927</xmax>
			<ymax>1087</ymax>
		</bndbox>
	</object>
</annotation>
