<annotation>
	<folder>rice</folder>
	<filename>rice_15.jpg</filename>
	<path>/Users/AndyWu/Documents/Docker/TensorFlow/chinese-cafeteria-food-recognition/data/rice/rice_15.jpg</path>
	<source>
		<database>Unknown</database>
	</source>
	<size>
		<width>600</width>
		<height>399</height>
		<depth>3</depth>
	</size>
	<segmented>0</segmented>
	<object>
		<name>rice</name>
		<pose>Unspecified</pose>
		<truncated>0</truncated>
		<difficult>0</difficult>
		<bndbox>
			<xmin>191</xmin>
			<ymin>98</ymin>
			<xmax>406</xmax>
			<ymax>255</ymax>
		</bndbox>
	</object>
</annotation>
