<annotation>
	<folder>anns</folder>
	<filename>1028_191030_0079.jpg</filename>
	<path>data/train/imgs/</path>
	<source>
		<database>Unknown</database>
	</source>
	<size>
		<width>720</width>
		<height>1280</height>
		<depth>3</depth>
	</size>
	<segmented>0</segmented>
	<object>
		<name>fried_eggs</name>
		<pose>Unspecified</pose>
		<truncated>0</truncated>
		<difficult>0</difficult>
		<bndbox>
			<xmin>248</xmin>
			<ymin>505</ymin>
			<xmax>695</xmax>
			<ymax>991</ymax>
		</bndbox>
	</object>
	<object>
		<name>water_spinach</name>
		<pose>Unspecified</pose>
		<truncated>1</truncated>
		<difficult>0</difficult>
		<bndbox>
			<xmin>1</xmin>
			<ymin>690</ymin>
			<xmax>315</xmax>
			<ymax>1095</ymax>
		</bndbox>
	</object>
	<object>
		<name>rice</name>
		<pose>Unspecified</pose>
		<truncated>0</truncated>
		<difficult>0</difficult>
		<bndbox>
			<xmin>81</xmin>
			<ymin>174</ymin>
			<xmax>462</xmax>
			<ymax>505</ymax>
		</bndbox>
	</object>
</annotation>
