<annotation>
	<folder>anns</folder>
	<filename>1028_191030_0066.jpg</filename>
	<path>data/train/imgs/</path>
	<source>
		<database>Unknown</database>
	</source>
	<size>
		<width>1478</width>
		<height>1108</height>
		<depth>3</depth>
	</size>
	<segmented>0</segmented>
	<object>
		<name>water_spinach</name>
		<pose>Unspecified</pose>
		<truncated>0</truncated>
		<difficult>0</difficult>
		<bndbox>
			<xmin>532</xmin>
			<ymin>672</ymin>
			<xmax>933</xmax>
			<ymax>962</ymax>
		</bndbox>
	</object>
	<object>
		<name>fried_eggs</name>
		<pose>Unspecified</pose>
		<truncated>0</truncated>
		<difficult>0</difficult>
		<bndbox>
			<xmin>900</xmin>
			<ymin>319</ymin>
			<xmax>1376</xmax>
			<ymax>842</ymax>
		</bndbox>
	</object>
	<object>
		<name>fried_chicken</name>
		<pose>Unspecified</pose>
		<truncated>0</truncated>
		<difficult>0</difficult>
		<bndbox>
			<xmin>421</xmin>
			<ymin>115</ymin>
			<xmax>994</xmax>
			<ymax>674</ymax>
		</bndbox>
	</object>
	<object>
		<name>rice</name>
		<pose>Unspecified</pose>
		<truncated>0</truncated>
		<difficult>0</difficult>
		<bndbox>
			<xmin>607</xmin>
			<ymin>73</ymin>
			<xmax>1100</xmax>
			<ymax>288</ymax>
		</bndbox>
	</object>
</annotation>
